django_agent_studio/__init__.py
django_agent_studio/apps.py
django_agent_studio/urls.py
django_agent_studio/views.py
django_agent_studio/agents/__init__.py
django_agent_studio/agents/builder.py
django_agent_studio/agents/dynamic.py
django_agent_studio/api/__init__.py
django_agent_studio/api/permissions.py
django_agent_studio/api/serializers.py
django_agent_studio/api/urls.py
django_agent_studio/api/views.py
django_agent_studio/management/__init__.py
django_agent_studio/management/commands/__init__.py
django_agent_studio/migrations/0001_initial.py
django_agent_studio/migrations/__init__.py
django_agent_studio/models/__init__.py
django_agent_studio/models/permissions.py
django_agent_studio/services/__init__.py
django_agent_studio/services/permissions.py
django_agent_studio/static/agent-frontend/chat-widget-markdown.js
django_agent_studio/static/agent-frontend/chat-widget.css
django_agent_studio/static/agent-frontend/chat-widget.js
django_agent_studio/static/django_agent_studio/js/builder.js
django_agent_studio/static/django_agent_studio/js/builder.js.map
django_agent_studio/static/django_agent_studio/js/style.css
django_agent_studio/templates/django_agent_studio/agent_list.html
django_agent_studio/templates/django_agent_studio/base.html
django_agent_studio/templates/django_agent_studio/builder.html
django_agent_studio/templates/django_agent_studio/collaborators.html
django_agent_studio/templates/django_agent_studio/home.html
django_agent_studio/templates/django_agent_studio/system_create.html
django_agent_studio/templates/django_agent_studio/system_list.html
django_agent_studio/templates/django_agent_studio/system_test.html
django_agent_studio/templates/django_agent_studio/test.html
django_agent_studio-0.3.3.dist-info/licenses/LICENSE
django_agent_studio-0.3.3.dist-info/METADATA
django_agent_studio-0.3.3.dist-info/WHEEL
django_agent_studio-0.3.3.dist-info/top_level.txt
django_agent_studio-0.3.3.dist-info/RECORD
