Metadata-Version: 2.4
Name: django-agent-studio
Version: 0.3.3
Summary: Visual agent builder and management studio for Django - build custom GPTs with a two-pane interface
Author: Chris Barry
License: Business Source License 1.1
Project-URL: Homepage, https://github.com/makemore/django-agent-studio
Project-URL: Documentation, https://github.com/makemore/django-agent-studio#readme
Project-URL: Repository, https://github.com/makemore/django-agent-studio
Keywords: django,ai,agent,llm,gpt,builder,studio
Classifier: Development Status :: 3 - Alpha
Classifier: Environment :: Web Environment
Classifier: Framework :: Django
Classifier: Framework :: Django :: 4.2
Classifier: Framework :: Django :: 5.0
Classifier: Intended Audience :: Developers
Classifier: Operating System :: OS Independent
Classifier: Programming Language :: Python :: 3
Classifier: Programming Language :: Python :: 3.10
Classifier: Programming Language :: Python :: 3.11
Classifier: Programming Language :: Python :: 3.12
Classifier: Topic :: Software Development :: Libraries :: Python Modules
Requires-Python: >=3.10
License-File: LICENSE
Requires-Dist: Django>=4.2
Requires-Dist: djangorestframework>=3.14
Requires-Dist: django-agent-runtime>=0.3.12
Provides-Extra: dev
Requires-Dist: pytest>=7.0; extra == "dev"
Requires-Dist: pytest-django>=4.5; extra == "dev"
Requires-Dist: pytest-asyncio>=0.21; extra == "dev"
Requires-Dist: pytest-cov>=4.0; extra == "dev"
Requires-Dist: black>=23.0; extra == "dev"
Requires-Dist: ruff>=0.1.0; extra == "dev"
Dynamic: license-file
